Metadata-Version: 2.1
Name: neural-search
Version: 0.6.3
Summary: Jina is the cloud-native neural search solution powered by the state-of-the-art AI and deep learning
Home-page: https://opensource.jina.ai
Author: Jina Dev Team
Author-email: dev-team@jina.ai
License: Apache 2.0
Download-URL: https://github.com/jina-ai/jina/tags
Keywords: jina cloud-native semantic query search index elastic neural-network encoding embedding serving docker container image video audio deep-learning
Platform: UNKNOWN
Classifier: Development Status :: 5 - Production/Stable
Classifier: Intended Audience :: Developers
Classifier: Intended Audience :: Education
Classifier: Intended Audience :: Science/Research
Classifier: Programming Language :: Python :: 3.7
Classifier: Programming Language :: Python :: 3.8
Classifier: Programming Language :: Python :: 3.9
Classifier: Programming Language :: Unix Shell
Classifier: Environment :: Console
Classifier: License :: OSI Approved :: Apache Software License
Classifier: Operating System :: OS Independent
Classifier: Topic :: Database :: Database Engines/Servers
Classifier: Topic :: Scientific/Engineering :: Artificial Intelligence
Classifier: Topic :: Internet :: WWW/HTTP :: Indexing/Search
Classifier: Topic :: Scientific/Engineering :: Image Recognition
Classifier: Topic :: Multimedia :: Video
Classifier: Topic :: Scientific/Engineering
Classifier: Topic :: Scientific/Engineering :: Mathematics
Classifier: Topic :: Software Development
Classifier: Topic :: Software Development :: Libraries
Classifier: Topic :: Software Development :: Libraries :: Python Modules
Provides-Extra: http
Provides-Extra: tensorflow-hub
Provides-Extra: nmslib
Provides-Extra: sklearn
Provides-Extra: gevent
Provides-Extra: pytest
Provides-Extra: all
Provides-Extra: flaky
Provides-Extra: numpy
Provides-Extra: scipy
Provides-Extra: tensorflow
Provides-Extra: onnx
Provides-Extra: flair
Provides-Extra: pytest-timeout
Provides-Extra: audio
Provides-Extra: match-py-ver
Provides-Extra: test
Provides-Extra: docker
Provides-Extra: tornado
Provides-Extra: torchvision
Provides-Extra: python-magic
Provides-Extra: ngt
Provides-Extra: uvloop
Provides-Extra: index
Provides-Extra: perf
Provides-Extra: cv
Provides-Extra: pytest-ordering
Provides-Extra: flask
Provides-Extra: Pillow
Provides-Extra: flask_cors
Provides-Extra: paddlepaddle
Provides-Extra: pymilvus
Provides-Extra: pytest-cov
Provides-Extra: network
Provides-Extra: py38
Provides-Extra: ruamel.yaml
Provides-Extra: pymongo[srv]
Provides-Extra: librosa
Provides-Extra: deepsegment
Provides-Extra: core
Provides-Extra: grpcio
Provides-Extra: sse
Provides-Extra: numeric
Provides-Extra: cookiecutter
Provides-Extra: pytest-repeat
Provides-Extra: py37
Provides-Extra: onnxruntime
Provides-Extra: devel
Provides-Extra: transformers
Provides-Extra: annoy
Provides-Extra: framework
Provides-Extra: jieba
Provides-Extra: mock
Provides-Extra: pyzmq
Provides-Extra: paddlehub
Provides-Extra: lz4
Provides-Extra: nlp
Provides-Extra: plyvel
Provides-Extra: pytest-xdist
Provides-Extra: hub
Provides-Extra: torch
Provides-Extra: protobuf
